setup.py
distributions/Binomialdistribution.py
distributions/Gaussiandistribution.py
distributions/Generaldistribution.py
distributions/__init__.py
gausebidistributions.egg-info/PKG-INFO
gausebidistributions.egg-info/SOURCES.txt
gausebidistributions.egg-info/dependency_links.txt
gausebidistributions.egg-info/not-zip-safe
gausebidistributions.egg-info/top_level.txt